tests/__init__.py
tests/test_live_stream.py
tests/test_resources.py
tests/test_utils.py
wowpy/__init__.py
wowpy/config.json
wowpy/constants.py
wowpy/exceptions.py
wowpy/livestreams.py
wowpy/mappings.py
wowpy/recordings.py
wowpy/resources.py
wowpy/schedules.py
wowpy/schemas.py
wowpy/targets.py
wowpy/transcoders.py
wowpy/utils.py
wowpy-0.1.30.dist-info/LICENSE
wowpy-0.1.30.dist-info/METADATA
wowpy-0.1.30.dist-info/WHEEL
wowpy-0.1.30.dist-info/top_level.txt
wowpy-0.1.30.dist-info/RECORD
