Metadata-Version: 2.1
Name: wowpy
Version: 0.1.30
Summary: Wowza python wrapper - wowpy
Home-page: https://github.com/d4n13lbc/wowpy
Author: Daniel Barragan
Author-email: dbarragan1331@gmail.com
License: UNKNOWN
Platform: UNKNOWN
Classifier: Programming Language :: Python :: 3
Classifier: License :: OSI Approved :: MIT License
Classifier: Operating System :: OS Independent
Requires-Dist: setuptools
Requires-Dist: requests
Requires-Dist: voluptuous
Requires-Dist: jsondiff
Requires-Dist: boltons
Requires-Dist: jsonmerge
